{
  "project_info": {
    "project_number": "623134389986",
    "project_id": "hedeiaty-415af",
    "storage_bucket": "hedeiaty-415af.firebasestorage.app"
  },
  "client": [
    {
      "client_info": {
        "mobilesdk_app_id": "1:623134389986:android:001d97c0dcd5799e2a90bb",
        "android_client_info": {
          "package_name": "com.example.hedieaty"
        }
      },
      "oauth_client": [],
      "api_key": [
        {
          "current_key": "AIzaSyBcdUitGgznqOEwu8EMkL4xPAYGezLV3kE"
        }
      ],
      "services": {
        "appinvite_service": {
          "other_platform_oauth_client": []
        }
      }
    }
  ],
  "configuration_version": "1"
}